package mt;

import android.util.Log;
import java.text.SimpleDateFormat;
import java.util.Arrays;
import java.util.concurrent.LinkedBlockingQueue;

public class Log229316
  extends Thread
{
  private static final ThreadLocal PARAMETER_BUFFER;
  private static final LinkedBlockingQueue QUEUE;
  private static final SimpleDateFormat TIME_FORMAT1 = new SimpleDateFormat("HH:mm:ss.SSS");
  private static final SimpleDateFormat TIME_FORMAT2 = new SimpleDateFormat("yyyyMMddHHmmssSSS");
  
  static
  {
    QUEUE = new LinkedBlockingQueue();
    PARAMETER_BUFFER = new ThreadLocal();
    Log229316 localLog229316 = new Log229316();
    localLog229316.setDaemon(true);
    localLog229316.start();
  }
  
  public static void a(char paramChar)
  {
    String str = String.valueOf(paramChar);
    Log5ECF72.a(str);
    LogE84000.a(str);
    z(str);
  }
  
  public static void a(double paramDouble)
  {
    String str = String.valueOf(paramDouble);
    Log5ECF72.a(str);
    LogE84000.a(str);
    z(str);
  }
  
  public static void a(float paramFloat)
  {
    String str = String.valueOf(paramFloat);
    Log5ECF72.a(str);
    LogE84000.a(str);
    z(str);
  }
  
  public static void a(int paramInt)
  {
    String str = String.valueOf(paramInt);
    Log5ECF72.a(str);
    LogE84000.a(str);
    z(str);
  }
  
  public static void a(long paramLong)
  {
    String str = String.valueOf(paramLong);
    Log5ECF72.a(str);
    LogE84000.a(str);
    z(str);
  }
  
  public static void a(Object paramObject)
  {
    paramObject = y(paramObject);
    Log5ECF72.a(paramObject);
    LogE84000.a(paramObject);
    z((String)paramObject);
  }
  
  public static void a(boolean paramBoolean)
  {
    String str = String.valueOf(paramBoolean);
    Log5ECF72.a(str);
    LogE84000.a(str);
    z(str);
  }
  
  public static void b()
  {
    ThreadLocal localThreadLocal = PARAMETER_BUFFER;
    z(((StringBuilder)localThreadLocal.get()).toString());
    localThreadLocal.remove();
  }
  
  public static void b1(char paramChar)
  {
    StringBuilder localStringBuilder = new StringBuilder();
    localStringBuilder.append("Parameter1: ");
    localStringBuilder.append(paramChar);
    x(localStringBuilder.toString());
  }
  
  public static void b1(double paramDouble)
  {
    StringBuilder localStringBuilder = new StringBuilder();
    localStringBuilder.append("Parameter1: ");
    localStringBuilder.append(paramDouble);
    x(localStringBuilder.toString());
  }
  
  public static void b1(float paramFloat)
  {
    StringBuilder localStringBuilder = new StringBuilder();
    localStringBuilder.append("Parameter1: ");
    localStringBuilder.append(paramFloat);
    x(localStringBuilder.toString());
  }
  
  public static void b1(int paramInt)
  {
    StringBuilder localStringBuilder = new StringBuilder();
    localStringBuilder.append("Parameter1: ");
    localStringBuilder.append(paramInt);
    x(localStringBuilder.toString());
  }
  
  public static void b1(long paramLong)
  {
    StringBuilder localStringBuilder = new StringBuilder();
    localStringBuilder.append("Parameter1: ");
    localStringBuilder.append(paramLong);
    x(localStringBuilder.toString());
  }
  
  public static void b1(Object paramObject)
  {
    StringBuilder localStringBuilder = new StringBuilder();
    localStringBuilder.append("Parameter1: ");
    paramObject = y(paramObject);
    Log5ECF72.a(paramObject);
    LogE84000.a(paramObject);
    localStringBuilder.append((String)paramObject);
    x(localStringBuilder.toString());
  }
  
  public static void b1(boolean paramBoolean)
  {
    StringBuilder localStringBuilder = new StringBuilder();
    localStringBuilder.append("Parameter1: ");
    localStringBuilder.append(paramBoolean);
    x(localStringBuilder.toString());
  }
  
  public static void b2(char paramChar)
  {
    StringBuilder localStringBuilder = new StringBuilder();
    localStringBuilder.append("Parameter2: ");
    localStringBuilder.append(paramChar);
    x(localStringBuilder.toString());
  }
  
  public static void b2(double paramDouble)
  {
    StringBuilder localStringBuilder = new StringBuilder();
    localStringBuilder.append("Parameter2: ");
    localStringBuilder.append(paramDouble);
    x(localStringBuilder.toString());
  }
  
  public static void b2(float paramFloat)
  {
    StringBuilder localStringBuilder = new StringBuilder();
    localStringBuilder.append("Parameter2: ");
    localStringBuilder.append(paramFloat);
    x(localStringBuilder.toString());
  }
  
  public static void b2(int paramInt)
  {
    StringBuilder localStringBuilder = new StringBuilder();
    localStringBuilder.append("Parameter2: ");
    localStringBuilder.append(paramInt);
    x(localStringBuilder.toString());
  }
  
  public static void b2(long paramLong)
  {
    StringBuilder localStringBuilder = new StringBuilder();
    localStringBuilder.append("Parameter2: ");
    localStringBuilder.append(paramLong);
    x(localStringBuilder.toString());
  }
  
  public static void b2(Object paramObject)
  {
    StringBuilder localStringBuilder = new StringBuilder();
    localStringBuilder.append("Parameter2: ");
    paramObject = y(paramObject);
    Log5ECF72.a(paramObject);
    LogE84000.a(paramObject);
    localStringBuilder.append((String)paramObject);
    x(localStringBuilder.toString());
  }
  
  public static void b2(boolean paramBoolean)
  {
    StringBuilder localStringBuilder = new StringBuilder();
    localStringBuilder.append("Parameter2: ");
    localStringBuilder.append(paramBoolean);
    x(localStringBuilder.toString());
  }
  
  public static void b3(char paramChar)
  {
    StringBuilder localStringBuilder = new StringBuilder();
    localStringBuilder.append("Parameter3: ");
    localStringBuilder.append(paramChar);
    x(localStringBuilder.toString());
  }
  
  public static void b3(double paramDouble)
  {
    StringBuilder localStringBuilder = new StringBuilder();
    localStringBuilder.append("Parameter3: ");
    localStringBuilder.append(paramDouble);
    x(localStringBuilder.toString());
  }
  
  public static void b3(float paramFloat)
  {
    StringBuilder localStringBuilder = new StringBuilder();
    localStringBuilder.append("Parameter3: ");
    localStringBuilder.append(paramFloat);
    x(localStringBuilder.toString());
  }
  
  public static void b3(int paramInt)
  {
    StringBuilder localStringBuilder = new StringBuilder();
    localStringBuilder.append("Parameter3: ");
    localStringBuilder.append(paramInt);
    x(localStringBuilder.toString());
  }
  
  public static void b3(long paramLong)
  {
    StringBuilder localStringBuilder = new StringBuilder();
    localStringBuilder.append("Parameter3: ");
    localStringBuilder.append(paramLong);
    x(localStringBuilder.toString());
  }
  
  public static void b3(Object paramObject)
  {
    StringBuilder localStringBuilder = new StringBuilder();
    localStringBuilder.append("Parameter3: ");
    paramObject = y(paramObject);
    Log5ECF72.a(paramObject);
    LogE84000.a(paramObject);
    localStringBuilder.append((String)paramObject);
    x(localStringBuilder.toString());
  }
  
  public static void b3(boolean paramBoolean)
  {
    StringBuilder localStringBuilder = new StringBuilder();
    localStringBuilder.append("Parameter3: ");
    localStringBuilder.append(paramBoolean);
    x(localStringBuilder.toString());
  }
  
  public static void b4(char paramChar)
  {
    StringBuilder localStringBuilder = new StringBuilder();
    localStringBuilder.append("Parameter4: ");
    localStringBuilder.append(paramChar);
    x(localStringBuilder.toString());
  }
  
  public static void b4(double paramDouble)
  {
    StringBuilder localStringBuilder = new StringBuilder();
    localStringBuilder.append("Parameter4: ");
    localStringBuilder.append(paramDouble);
    x(localStringBuilder.toString());
  }
  
  public static void b4(float paramFloat)
  {
    StringBuilder localStringBuilder = new StringBuilder();
    localStringBuilder.append("Parameter4: ");
    localStringBuilder.append(paramFloat);
    x(localStringBuilder.toString());
  }
  
  public static void b4(int paramInt)
  {
    StringBuilder localStringBuilder = new StringBuilder();
    localStringBuilder.append("Parameter4: ");
    localStringBuilder.append(paramInt);
    x(localStringBuilder.toString());
  }
  
  public static void b4(long paramLong)
  {
    StringBuilder localStringBuilder = new StringBuilder();
    localStringBuilder.append("Parameter4: ");
    localStringBuilder.append(paramLong);
    x(localStringBuilder.toString());
  }
  
  public static void b4(Object paramObject)
  {
    StringBuilder localStringBuilder = new StringBuilder();
    localStringBuilder.append("Parameter4: ");
    paramObject = y(paramObject);
    Log5ECF72.a(paramObject);
    LogE84000.a(paramObject);
    localStringBuilder.append((String)paramObject);
    x(localStringBuilder.toString());
  }
  
  public static void b4(boolean paramBoolean)
  {
    StringBuilder localStringBuilder = new StringBuilder();
    localStringBuilder.append("Parameter4: ");
    localStringBuilder.append(paramBoolean);
    x(localStringBuilder.toString());
  }
  
  public static void b5(char paramChar)
  {
    StringBuilder localStringBuilder = new StringBuilder();
    localStringBuilder.append("Parameter5: ");
    localStringBuilder.append(paramChar);
    x(localStringBuilder.toString());
  }
  
  public static void b5(double paramDouble)
  {
    StringBuilder localStringBuilder = new StringBuilder();
    localStringBuilder.append("Parameter5: ");
    localStringBuilder.append(paramDouble);
    x(localStringBuilder.toString());
  }
  
  public static void b5(float paramFloat)
  {
    StringBuilder localStringBuilder = new StringBuilder();
    localStringBuilder.append("Parameter5: ");
    localStringBuilder.append(paramFloat);
    x(localStringBuilder.toString());
  }
  
  public static void b5(int paramInt)
  {
    StringBuilder localStringBuilder = new StringBuilder();
    localStringBuilder.append("Parameter5: ");
    localStringBuilder.append(paramInt);
    x(localStringBuilder.toString());
  }
  
  public static void b5(long paramLong)
  {
    StringBuilder localStringBuilder = new StringBuilder();
    localStringBuilder.append("Parameter5: ");
    localStringBuilder.append(paramLong);
    x(localStringBuilder.toString());
  }
  
  public static void b5(Object paramObject)
  {
    StringBuilder localStringBuilder = new StringBuilder();
    localStringBuilder.append("Parameter5: ");
    paramObject = y(paramObject);
    Log5ECF72.a(paramObject);
    LogE84000.a(paramObject);
    localStringBuilder.append((String)paramObject);
    x(localStringBuilder.toString());
  }
  
  public static void b5(boolean paramBoolean)
  {
    StringBuilder localStringBuilder = new StringBuilder();
    localStringBuilder.append("Parameter5: ");
    localStringBuilder.append(paramBoolean);
    x(localStringBuilder.toString());
  }
  
  public static void b6(char paramChar)
  {
    StringBuilder localStringBuilder = new StringBuilder();
    localStringBuilder.append("Parameter6: ");
    localStringBuilder.append(paramChar);
    x(localStringBuilder.toString());
  }
  
  public static void b6(double paramDouble)
  {
    StringBuilder localStringBuilder = new StringBuilder();
    localStringBuilder.append("Parameter6: ");
    localStringBuilder.append(paramDouble);
    x(localStringBuilder.toString());
  }
  
  public static void b6(float paramFloat)
  {
    StringBuilder localStringBuilder = new StringBuilder();
    localStringBuilder.append("Parameter6: ");
    localStringBuilder.append(paramFloat);
    x(localStringBuilder.toString());
  }
  
  public static void b6(int paramInt)
  {
    StringBuilder localStringBuilder = new StringBuilder();
    localStringBuilder.append("Parameter6: ");
    localStringBuilder.append(paramInt);
    x(localStringBuilder.toString());
  }
  
  public static void b6(long paramLong)
  {
    StringBuilder localStringBuilder = new StringBuilder();
    localStringBuilder.append("Parameter6: ");
    localStringBuilder.append(paramLong);
    x(localStringBuilder.toString());
  }
  
  public static void b6(Object paramObject)
  {
    StringBuilder localStringBuilder = new StringBuilder();
    localStringBuilder.append("Parameter6: ");
    paramObject = y(paramObject);
    Log5ECF72.a(paramObject);
    LogE84000.a(paramObject);
    localStringBuilder.append((String)paramObject);
    x(localStringBuilder.toString());
  }
  
  public static void b6(boolean paramBoolean)
  {
    StringBuilder localStringBuilder = new StringBuilder();
    localStringBuilder.append("Parameter6: ");
    localStringBuilder.append(paramBoolean);
    x(localStringBuilder.toString());
  }
  
  public static void printStackTrace()
  {
    String str = Log.getStackTraceString(new Exception("InjectedLog.printStackTrace"));
    Log5ECF72.a(str);
    LogE84000.a(str);
    z(str);
  }
  
  private static void x(String paramString)
  {
    ThreadLocal localThreadLocal = PARAMETER_BUFFER;
    StringBuilder localStringBuilder2 = (StringBuilder)localThreadLocal.get();
    StringBuilder localStringBuilder1 = localStringBuilder2;
    if (localStringBuilder2 == null)
    {
      localStringBuilder1 = new StringBuilder();
      localThreadLocal.set(localStringBuilder1);
    }
    if (localStringBuilder1.length() > 0) {
      localStringBuilder1.append('\n');
    }
    localStringBuilder1.append(paramString);
  }
  
  private static String y(Object paramObject)
  {
    if (paramObject == null) {
      return "null";
    }
    Class localClass = paramObject.getClass();
    if (localClass.isArray())
    {
      if (localClass == byte[].class)
      {
        paramObject = Arrays.toString((byte[])paramObject);
        Log5ECF72.a(paramObject);
        LogE84000.a(paramObject);
        return (String)paramObject;
      }
      if (localClass == short[].class)
      {
        paramObject = Arrays.toString((short[])paramObject);
        Log5ECF72.a(paramObject);
        LogE84000.a(paramObject);
        return (String)paramObject;
      }
      if (localClass == int[].class)
      {
        paramObject = Arrays.toString((int[])paramObject);
        Log5ECF72.a(paramObject);
        LogE84000.a(paramObject);
        return (String)paramObject;
      }
      if (localClass == long[].class)
      {
        paramObject = Arrays.toString((long[])paramObject);
        Log5ECF72.a(paramObject);
        LogE84000.a(paramObject);
        return (String)paramObject;
      }
      if (localClass == char[].class)
      {
        paramObject = Arrays.toString((char[])paramObject);
        Log5ECF72.a(paramObject);
        LogE84000.a(paramObject);
        return (String)paramObject;
      }
      if (localClass == float[].class)
      {
        paramObject = Arrays.toString((float[])paramObject);
        Log5ECF72.a(paramObject);
        LogE84000.a(paramObject);
        return (String)paramObject;
      }
      if (localClass == double[].class)
      {
        paramObject = Arrays.toString((double[])paramObject);
        Log5ECF72.a(paramObject);
        LogE84000.a(paramObject);
        return (String)paramObject;
      }
      if (localClass == boolean[].class)
      {
        paramObject = Arrays.toString((boolean[])paramObject);
        Log5ECF72.a(paramObject);
        LogE84000.a(paramObject);
        return (String)paramObject;
      }
      paramObject = Arrays.deepToString((Object[])paramObject);
      Log5ECF72.a(paramObject);
      LogE84000.a(paramObject);
      return (String)paramObject;
    }
    return paramObject.toString();
  }
  
  private static void z(String paramString)
  {
    String str = "[TIME][CLASS][METHOD][LOCATION][RESULT]\n[LOCATION][METHOD][CLASS][LOCATION]\n";
    if ("[TIME][CLASS][METHOD][LOCATION][RESULT]\n[LOCATION][METHOD][CLASS][LOCATION]\n".contains("[TIME]")) {
      str = "[TIME][CLASS][METHOD][LOCATION][RESULT]\n[LOCATION][METHOD][CLASS][LOCATION]\n".replace("[TIME]", TIME_FORMAT1.format(Long.valueOf(System.currentTimeMillis())));
    }
    StackTraceElement localStackTraceElement = new Throwable().getStackTrace()[2];
    Object localObject2 = localStackTraceElement.getFileName();
    Object localObject1 = localObject2;
    if (localObject2 == null) {
      localObject1 = "Unknown Source";
    }
    int i = localStackTraceElement.getLineNumber();
    localObject2 = localObject1;
    if (i >= 0)
    {
      localObject2 = new StringBuilder();
      ((StringBuilder)localObject2).append((String)localObject1);
      ((StringBuilder)localObject2).append(":");
      ((StringBuilder)localObject2).append(i);
      localObject2 = ((StringBuilder)localObject2).toString();
    }
    paramString = str.replace("[RESULT]", paramString).replace("[CLASS]", localStackTraceElement.getClassName()).replace("[METHOD]", localStackTraceElement.getMethodName()).replace("[LOCATION]", (CharSequence)localObject2);
    QUEUE.offer(paramString);
  }
  
  /* Error */
  public void run()
  {
    // Byte code:
    //   0: aconst_null
    //   1: astore_1
    //   2: ldc_w 298
    //   5: ldc_w 300
    //   8: invokestatic 306	android/os/Environment:getExternalStorageDirectory	()Ljava/io/File;
    //   11: invokevirtual 311	java/io/File:getPath	()Ljava/lang/String;
    //   14: invokevirtual 256	java/lang/String:replace	(Ljava/lang/CharSequence;Ljava/lang/CharSequence;)Ljava/lang/String;
    //   17: ldc_w 313
    //   20: ldc_w 315
    //   23: invokevirtual 256	java/lang/String:replace	(Ljava/lang/CharSequence;Ljava/lang/CharSequence;)Ljava/lang/String;
    //   26: ldc -22
    //   28: getstatic 27	mt/Log229316:TIME_FORMAT2	Ljava/text/SimpleDateFormat;
    //   31: invokestatic 244	java/lang/System:currentTimeMillis	()J
    //   34: invokestatic 249	java/lang/Long:valueOf	(J)Ljava/lang/Long;
    //   37: invokevirtual 252	java/text/SimpleDateFormat:format	(Ljava/lang/Object;)Ljava/lang/String;
    //   40: invokevirtual 256	java/lang/String:replace	(Ljava/lang/CharSequence;Ljava/lang/CharSequence;)Ljava/lang/String;
    //   43: bipush 92
    //   45: bipush 47
    //   47: invokevirtual 318	java/lang/String:replace	(CC)Ljava/lang/String;
    //   50: ldc_w 320
    //   53: ldc_w 322
    //   56: invokevirtual 256	java/lang/String:replace	(Ljava/lang/CharSequence;Ljava/lang/CharSequence;)Ljava/lang/String;
    //   59: astore_3
    //   60: aconst_null
    //   61: astore_2
    //   62: new 308	java/io/File
    //   65: astore 4
    //   67: aload 4
    //   69: aload_3
    //   70: invokespecial 323	java/io/File:<init>	(Ljava/lang/String;)V
    //   73: aload 4
    //   75: invokevirtual 326	java/io/File:getParentFile	()Ljava/io/File;
    //   78: astore_3
    //   79: aload_3
    //   80: ifnull +8 -> 88
    //   83: aload_3
    //   84: invokevirtual 329	java/io/File:mkdirs	()Z
    //   87: pop
    //   88: new 331	java/io/FileOutputStream
    //   91: astore_3
    //   92: aload_3
    //   93: aload 4
    //   95: iconst_1
    //   96: invokespecial 334	java/io/FileOutputStream:<init>	(Ljava/io/File;Z)V
    //   99: aload_3
    //   100: astore_1
    //   101: goto +8 -> 109
    //   104: astore_2
    //   105: aload_2
    //   106: invokevirtual 336	java/io/IOException:printStackTrace	()V
    //   109: aload_1
    //   110: astore_3
    //   111: aload_1
    //   112: ifnonnull +94 -> 206
    //   115: new 308	java/io/File
    //   118: astore_3
    //   119: aload_3
    //   120: ldc_w 338
    //   123: invokespecial 323	java/io/File:<init>	(Ljava/lang/String;)V
    //   126: new 308	java/io/File
    //   129: astore 4
    //   131: new 97	java/lang/StringBuilder
    //   134: astore_1
    //   135: aload_1
    //   136: invokespecial 106	java/lang/StringBuilder:<init>	()V
    //   139: aload_1
    //   140: getstatic 27	mt/Log229316:TIME_FORMAT2	Ljava/text/SimpleDateFormat;
    //   143: invokestatic 244	java/lang/System:currentTimeMillis	()J
    //   146: invokestatic 249	java/lang/Long:valueOf	(J)Ljava/lang/Long;
    //   149: invokevirtual 252	java/text/SimpleDateFormat:format	(Ljava/lang/Object;)Ljava/lang/String;
    //   152: invokevirtual 112	java/lang/StringBuilder:append	(Ljava/lang/String;)Ljava/lang/StringBuilder;
    //   155: pop
    //   156: aload_1
    //   157: ldc_w 340
    //   160: invokevirtual 112	java/lang/StringBuilder:append	(Ljava/lang/String;)Ljava/lang/StringBuilder;
    //   163: pop
    //   164: aload 4
    //   166: aload_3
    //   167: aload_1
    //   168: invokevirtual 101	java/lang/StringBuilder:toString	()Ljava/lang/String;
    //   171: invokespecial 343	java/io/File:<init>	(Ljava/io/File;Ljava/lang/String;)V
    //   174: aload_3
    //   175: invokevirtual 329	java/io/File:mkdirs	()Z
    //   178: pop
    //   179: new 331	java/io/FileOutputStream
    //   182: dup
    //   183: aload 4
    //   185: invokespecial 346	java/io/FileOutputStream:<init>	(Ljava/io/File;)V
    //   188: astore_3
    //   189: goto +17 -> 206
    //   192: astore_1
    //   193: aload_1
    //   194: invokevirtual 336	java/io/IOException:printStackTrace	()V
    //   197: new 348	java/lang/RuntimeException
    //   200: dup
    //   201: aload_2
    //   202: invokespecial 351	java/lang/RuntimeException:<init>	(Ljava/lang/Throwable;)V
    //   205: athrow
    //   206: invokestatic 357	java/nio/charset/Charset:defaultCharset	()Ljava/nio/charset/Charset;
    //   209: astore_2
    //   210: getstatic 33	mt/Log229316:QUEUE	Ljava/util/concurrent/LinkedBlockingQueue;
    //   213: astore_1
    //   214: aload_3
    //   215: aload_1
    //   216: invokevirtual 360	java/util/concurrent/LinkedBlockingQueue:take	()Ljava/lang/Object;
    //   219: checkcast 52	java/lang/String
    //   222: aload_2
    //   223: invokevirtual 364	java/lang/String:getBytes	(Ljava/nio/charset/Charset;)[B
    //   226: invokevirtual 368	java/io/FileOutputStream:write	([B)V
    //   229: aload_1
    //   230: invokevirtual 371	java/util/concurrent/LinkedBlockingQueue:isEmpty	()Z
    //   233: ifeq +7 -> 240
    //   236: aload_3
    //   237: invokevirtual 374	java/io/FileOutputStream:flush	()V
    //   240: goto -30 -> 210
    //   243: astore_1
    //   244: new 348	java/lang/RuntimeException
    //   247: dup
    //   248: aload_1
    //   249: invokespecial 351	java/lang/RuntimeException:<init>	(Ljava/lang/Throwable;)V
    //   252: athrow
    // Local variable table:
    //   start	length	slot	name	signature
    //   0	253	0	this	Log229316
    //   1	167	1	localObject1	Object
    //   192	2	1	localIOException1	java.io.IOException
    //   213	17	1	localLinkedBlockingQueue	LinkedBlockingQueue
    //   243	6	1	localException	Exception
    //   61	1	2	localObject2	Object
    //   104	98	2	localIOException2	java.io.IOException
    //   209	14	2	localCharset	java.nio.charset.Charset
    //   59	178	3	localObject3	Object
    //   65	119	4	localFile	java.io.File
    // Exception table:
    //   from	to	target	type
    //   62	79	104	java/io/IOException
    //   83	88	104	java/io/IOException
    //   88	99	104	java/io/IOException
    //   115	189	192	java/io/IOException
    //   206	210	243	java/lang/Exception
    //   210	240	243	java/lang/Exception
  }
}


/* Location:              /home/icat/Documents/digital-awareness/src/undangan-pernikahan-dex2jar.jar!/mt/Log229316.class
 * Java compiler version: 6 (50.0)
 * JD-Core Version:       0.7.1
 */